nonebot_plugin_chatppt/.DS_Store
nonebot_plugin_chatppt/__init__.py
nonebot_plugin_chatppt/config.py
nonebot_plugin_chatppt/core.py
nonebot_plugin_chatppt-0.1.1.dist-info/WHEEL
nonebot_plugin_chatppt-0.1.1.dist-info/METADATA
nonebot_plugin_chatppt-0.1.1.dist-info/RECORD
