Metadata-Version: 2.1
Name: nonebot-plugin-chatppt
Version: 0.1.1
Summary: A nonebot plugin for generating PPT slides from ChatGPT
License: MIT
Author: Alpaca
Author-email: alpaca@bupt.edu.cn
Requires-Python: >=3.8,<4.0
Classifier: License :: OSI Approved :: MIT License
Classifier: Programming Language :: Python :: 3
Classifier: Programming Language :: Python :: 3.8
Classifier: Programming Language :: Python :: 3.9
Classifier: Programming Language :: Python :: 3.10
Classifier: Programming Language :: Python :: 3.11
Requires-Dist: icrawler (>=0.6.6,<0.7.0)
Requires-Dist: nonebot-adapter-onebot (>=2.2.1,<3.0.0)
Requires-Dist: nonebot2 (>=2.0.0rc3,<3.0.0)
Requires-Dist: openai (>=0.27.1,<0.28.0)
Requires-Dist: python-pptx (>=0.6.21,<0.7.0)
